fugue_fe/__init__.py
fugue_fe/dummy.py
fugue_fe_version/__init__.py
tests/__init__.py
tests/fugue_fe/__init__.py
tests/fugue_fe/test_dummy.py
fugue_fe-0.0.1.dist-info/LICENSE
fugue_fe-0.0.1.dist-info/METADATA
fugue_fe-0.0.1.dist-info/WHEEL
fugue_fe-0.0.1.dist-info/top_level.txt
fugue_fe-0.0.1.dist-info/RECORD
